nbcelltests/__init__.py
nbcelltests/__main__.py
nbcelltests/define.py
nbcelltests/extension.py
nbcelltests/shared.py
nbcelltests/test.py
nbcelltests/tests_vendored.py
nbcelltests/lint/__init__.py
nbcelltests/lint/rules.py
nbcelltests/tests/__init__.py
nbcelltests/tests/_broken_magics.ipynb
nbcelltests/tests/_cell_counting.ipynb
nbcelltests/tests/_cell_coverage.ipynb
nbcelltests/tests/_cell_error.ipynb
nbcelltests/tests/_cell_not_injected_or_mocked.ipynb
nbcelltests/tests/_cumulative_run.ipynb
nbcelltests/tests/_empty_cell_with_test.ipynb
nbcelltests/tests/_emptyast_cell_with_test.ipynb
nbcelltests/tests/_input_cell_multiline_string.ipynb
nbcelltests/tests/_input_cell_newline_string.ipynb
nbcelltests/tests/_input_test_injection_comment.ipynb
nbcelltests/tests/_input_test_multiline_string.ipynb
nbcelltests/tests/_input_test_newline_string.ipynb
nbcelltests/tests/_kernel_check.ipynb
nbcelltests/tests/_kernel_check1.ipynb
nbcelltests/tests/_kernel_cwd.ipynb
nbcelltests/tests/_lint_disable.ipynb
nbcelltests/tests/_lint_disable_empty_cell.ipynb
nbcelltests/tests/_no_code_cells.ipynb
nbcelltests/tests/_non_code_cell.ipynb
nbcelltests/tests/_skips.ipynb
nbcelltests/tests/_test_error.ipynb
nbcelltests/tests/_test_fail.ipynb
nbcelltests/tests/basic.ipynb
nbcelltests/tests/magics.ipynb
nbcelltests/tests/more.ipynb
nbcelltests/tests/test_all.py
nbcelltests/tests/test_extension.py
nbcelltests/tests/test_init.py
nbcelltests/tests/test_lint.py
nbcelltests/tests/test_shared.py
nbcelltests-0.3.2.data/data/share/jupyter/labextensions/nbcelltests/build_log.json
nbcelltests-0.3.2.data/data/share/jupyter/labextensions/nbcelltests/package.json
nbcelltests-0.3.2.data/data/share/jupyter/labextensions/nbcelltests/schemas/nbcelltests/package.json.orig
nbcelltests-0.3.2.data/data/share/jupyter/labextensions/nbcelltests/static/lib_index_js.d5be332c5a38e8256a6e.js
nbcelltests-0.3.2.data/data/share/jupyter/labextensions/nbcelltests/static/lib_index_js.d5be332c5a38e8256a6e.js.map
nbcelltests-0.3.2.dist-info/METADATA
nbcelltests-0.3.2.dist-info/WHEEL
nbcelltests-0.3.2.dist-info/entry_points.txt
nbcelltests-0.3.2.dist-info/licenses/AUTHORS
nbcelltests-0.3.2.dist-info/licenses/LICENSE
nbcelltests-0.3.2.dist-info/RECORD
