Metadata-Version: 2.3
Name: nbcelltests
Version: 0.3.2
Summary: Cell-by-cell tests for JupyterLab
Project-URL: Repository, https://github.com/jpmorganchase/nbcelltests
Project-URL: Homepage, https://github.com/jpmorganchase/nbcelltests
Author-email: The nbcelltests authors <t.paine154@gmail.com>
License:                                  Apache License
License-File: AUTHORS
License-File: LICENSE
Keywords: Celltests,Jupyter,JupyterLab,Notebook,Notebooks,Testing,Tests
Classifier: Development Status :: 4 - Beta
Classifier: Framework :: Jupyter
Classifier: Framework :: Jupyter :: JupyterLab
Classifier: License :: OSI Approved :: Apache Software License
Classifier: Programming Language :: Python
Classifier: Programming Language :: Python :: 3
Classifier: Programming Language :: Python :: 3.9
Classifier: Programming Language :: Python :: 3.10
Classifier: Programming Language :: Python :: 3.11
Classifier: Programming Language :: Python :: 3.12
Requires-Python: >=3.8
Requires-Dist: flake8
Requires-Dist: jupyter-server
Requires-Dist: jupyterlab
Requires-Dist: nbconvert
Requires-Dist: nbformat>=4.0.0
Requires-Dist: nbval>=0.9.1
Requires-Dist: notebook
Requires-Dist: parameterized
Requires-Dist: pytest-cov
Requires-Dist: pytest-html>=4
Requires-Dist: pytest>=4.4.0
Provides-Extra: develop
Requires-Dist: check-manifest; extra == 'develop'
Requires-Dist: isort<6,>=5; extra == 'develop'
Requires-Dist: jupyterlab<5,>=4; extra == 'develop'
Requires-Dist: pytest; extra == 'develop'
Requires-Dist: pytest-cov; extra == 'develop'
Requires-Dist: ruff<0.5,>=0.3; extra == 'develop'
Provides-Extra: test
Requires-Dist: pytest; extra == 'test'
Requires-Dist: pytest-cov; extra == 'test'
